mmdit/__init__.py
mmdit/adaptive_attention.py
mmdit/mmdit_generalized_pytorch.py
mmdit/mmdit_pytorch.py
mmdit-0.2.2.dist-info/METADATA
mmdit-0.2.2.dist-info/WHEEL
mmdit-0.2.2.dist-info/licenses/LICENSE
mmdit-0.2.2.dist-info/RECORD
