Metadata-Version: 2.4
Name: mmdit
Version: 0.2.2
Summary: MMDiT
Project-URL: Homepage, https://pypi.org/project/mmdit/
Project-URL: Repository, https://github.com/lucidrains/mmdit
Author-email: Phil Wang <lucidrains@gmail.com>
License: MIT License
License-File: LICENSE
Keywords: artificial intelligence,attention mechanism,deep learning,multi-modal transformer
Classifier: Development Status :: 4 - Beta
Classifier: Intended Audience :: Developers
Classifier: License :: OSI Approved :: MIT License
Classifier: Programming Language :: Python :: 3.9
Classifier: Topic :: Scientific/Engineering :: Artificial Intelligence
Requires-Python: >=3.9
Requires-Dist: einops>=0.8.0
Requires-Dist: hyper-connections>=0.0.15
Requires-Dist: torch>=2.0
Requires-Dist: x-transformers>=1.31.9
Provides-Extra: examples
